<?xml version="1.0" encoding="utf-8"?>
<odoo>
    <data>

       <!-- physical_status -->
    <record model="ir.ui.view" id="soe_fixed_assets.physical_status_list"> <!-- Cada vista tambien es almacenado como modelo por lo tanto c/u debe tener un id unico-->
      <field name="name">fixed assets physical_status list</field>
      <field name="model">soe_fixed_assets.physical_status</field> <!--El modelo al que pertenece esta vista -->
      <field name="arch" type="xml">
        <list>
          <field name="name"/>
          <field name="description"/>
<!--          <field name="created_by"/>-->

        </list>
      </field>
    </record>

    <record model="ir.ui.view" id="soe_fixed_assets.physical_status_form"> <!-- Cada vista tambien es almacenado como modelo por lo tanto c/u debe tener un id unico-->
      <field name="name">fixed assets physical_status form</field>
      <field name="model">soe_fixed_assets.physical_status</field> <!--El modelo al que pertenece esta vista -->
      <field name="arch" type="xml">
        <form>
          <group>
            <field name="name"/>
            <field name="description"/>
<!--            <field name="created_by"/>-->
          </group>
        </form>
      </field>
    </record>

    </data>
</odoo>